setup.py
credstash_cache/__init__.py
credstash_cache.egg-info/PKG-INFO
credstash_cache.egg-info/SOURCES.txt
credstash_cache.egg-info/dependency_links.txt
credstash_cache.egg-info/not-zip-safe
credstash_cache.egg-info/requires.txt
credstash_cache.egg-info/top_level.txt